auth0/__init__.py
auth0/admin.py
auth0/apps.py
auth0/backend.py
auth0/models.py
auth0/urls.py
auth0/views.py
auth0/migrations/__init__.py
auth0/templates/admin/login.html
auth0/templates/django_auth0_auth/index.html
django_auth0_authbackend-0.2.0.dist-info/METADATA
django_auth0_authbackend-0.2.0.dist-info/WHEEL
django_auth0_authbackend-0.2.0.dist-info/RECORD
