Metadata-Version: 2.4
Name: django-auth0-authbackend
Version: 0.2.0
Summary: Auth0 Authentication Backend for Django
Author-email: Andy Reagan <andy@andyreagan.com>
License-Expression: MIT
Keywords: auth0,django,django-auth,django-auth0
Classifier: Development Status :: 4 - Beta
Classifier: Framework :: Django
Classifier: Framework :: Django :: 5.0
Classifier: Framework :: Django :: 5.1
Classifier: Framework :: Django :: 5.2
Classifier: License :: OSI Approved :: MIT License
Classifier: Programming Language :: Python :: 3
Classifier: Programming Language :: Python :: 3.11
Classifier: Programming Language :: Python :: 3.12
Classifier: Programming Language :: Python :: 3.13
Classifier: Topic :: Utilities
Requires-Python: >=3.11
Requires-Dist: authlib>=1.0.0
Requires-Dist: django>=5.0.0
Requires-Dist: requests>=2.0.0
Provides-Extra: test
Requires-Dist: playwright>=1.40.0; extra == 'test'
Requires-Dist: pytest-django>=4.0.0; extra == 'test'
Requires-Dist: pytest-playwright>=0.4.0; extra == 'test'
Requires-Dist: pytest>=7.0.0; extra == 'test'
Requires-Dist: python-dotenv>=1.0.0; extra == 'test'
